<?xml version="1.0" encoding="UTF-8"?>
<MetaDataObject xmlns="http://v8.1c.ru/8.3/MDClasses" xmlns:app="http://v8.1c.ru/8.2/managed-application/core" xmlns:cfg="http://v8.1c.ru/8.1/data/enterprise/current-config" xmlns:cmi="http://v8.1c.ru/8.2/managed-application/cmi" xmlns:ent="http://v8.1c.ru/8.1/data/enterprise" xmlns:lf="http://v8.1c.ru/8.2/managed-application/logform" xmlns:style="http://v8.1c.ru/8.1/data/ui/style" xmlns:sys="http://v8.1c.ru/8.1/data/ui/fonts/system" xmlns:v8="http://v8.1c.ru/8.1/data/core" xmlns:v8ui="http://v8.1c.ru/8.1/data/ui" xmlns:web="http://v8.1c.ru/8.1/data/ui/colors/web" xmlns:win="http://v8.1c.ru/8.1/data/ui/colors/windows" xmlns:xen="http://v8.1c.ru/8.3/xcf/enums" xmlns:xpr="http://v8.1c.ru/8.3/xcf/predef" xmlns:xr="http://v8.1c.ru/8.3/xcf/readable" xmlns:xs="http://www.w3.org/2001/XMLSchema" xmlns:xsi="http://www.w3.org/2001/XMLSchema-instance" version="2.12">
	<EventSubscription uuid="ca4b39c2-dbab-4c86-aa05-ce1f4c34211f">
		<Properties>
			<Name>АвтономнаяРаботаЗарегистрироватьУдаление</Name>
			<Synonym>
				<v8:item>
					<v8:lang>ru</v8:lang>
					<v8:content>Зарегистрировать удаление для автономной работы</v8:content>
				</v8:item>
				<v8:item>
					<v8:lang>uk</v8:lang>
					<v8:content>Зареєструвати вилучення для автономної роботи</v8:content>
				</v8:item>
			</Synonym>
			<Comment/>
			<Source>
				<v8:Type>cfg:DocumentObject.ВыгрузкаРегламентированныхОтчетов</v8:Type>
				<v8:Type>cfg:CatalogObject.Организации</v8:Type>
				<v8:Type>cfg:DocumentObject.ОтчетПроизводстваЗаСмену</v8:Type>
				<v8:Type>cfg:DocumentObject.ИзменениеНалоговогоНазначенияЗапасов</v8:Type>
				<v8:Type>cfg:CatalogObject.СтатьиОтсроченныхНалоговыхАктивовИОбязательств</v8:Type>
				<v8:Type>cfg:CatalogObject.ПричиныСписанияОС</v8:Type>
				<v8:Type>cfg:CatalogObject.ПлатежноеПоручениеПрисоединенныеФайлы</v8:Type>
				<v8:Type>cfg:DocumentObject.СписаниеСРасчетногоСчета</v8:Type>
				<v8:Type>cfg:DocumentObject.ПлатежныйОрдерПоступлениеДенежныхСредств</v8:Type>
				<v8:Type>cfg:DocumentObject.ПриходныйКассовыйОрдер</v8:Type>
				<v8:Type>cfg:CatalogObject.ОсновныеСредства</v8:Type>
				<v8:Type>cfg:DocumentObject.НалоговаяНакладная</v8:Type>
				<v8:Type>cfg:CatalogObject.НоменклатураГТД</v8:Type>
				<v8:Type>cfg:CatalogObject.ВерсииФайлов</v8:Type>
				<v8:Type>cfg:CatalogObject.ЗарплатныеПроекты</v8:Type>
				<v8:Type>cfg:CatalogObject.ФизическиеЛица</v8:Type>
				<v8:Type>cfg:DocumentObject.УстановкаКоэффициентаПропорциональногоОтнесенияНДСНаКредит</v8:Type>
				<v8:Type>cfg:DocumentObject.СписаниеМалоценныхАктивовИзЭксплуатации</v8:Type>
				<v8:Type>cfg:DocumentObject.ВыработкаНМА</v8:Type>
				<v8:Type>cfg:CatalogObject.ПапкиФайлов</v8:Type>
				<v8:Type>cfg:DocumentObject.ОтражениеЗарплатыВУчете</v8:Type>
				<v8:Type>cfg:DocumentObject.СписаниеНМА</v8:Type>
				<v8:Type>cfg:CatalogObject.СтраныМира</v8:Type>
				<v8:Type>cfg:DocumentObject.Приложение2КНалоговойНакладной</v8:Type>
				<v8:Type>cfg:CatalogObject.СтепениРодстваФизЛиц</v8:Type>
				<v8:Type>cfg:DocumentObject.ПоступлениеНМА</v8:Type>
				<v8:Type>cfg:CatalogObject.ПоступлениеНаРасчетныйСчетПрисоединенныеФайлы</v8:Type>
				<v8:Type>cfg:CatalogObject.ВозвратТоваровОтПокупателяПрисоединенныеФайлы</v8:Type>
				<v8:Type>cfg:DocumentObject.СчетНаОплатуПокупателю</v8:Type>
				<v8:Type>cfg:CatalogObject.ПередачаТоваровПрисоединенныеФайлы</v8:Type>
				<v8:Type>cfg:DocumentObject.ВозвратТоваровПоставщику</v8:Type>
				<v8:Type>cfg:CatalogObject.ОбъектыСтроительства</v8:Type>
				<v8:Type>cfg:CatalogObject.РегистрУчетаПрисоединенныеФайлы</v8:Type>
				<v8:Type>cfg:CatalogObject.УчетныеЗаписиЭлектроннойПочты</v8:Type>
				<v8:Type>cfg:CatalogObject.ОтражениеЗарплатыВБухучетеПрисоединенныеФайлы</v8:Type>
				<v8:Type>cfg:CatalogObject.РеализацияТоваровУслугПрисоединенныеФайлы</v8:Type>
				<v8:Type>cfg:CatalogObject.ПрочиеНеоборотныеАктивы</v8:Type>
				<v8:Type>cfg:DocumentObject.НачислениеЗарплаты</v8:Type>
				<v8:Type>cfg:DocumentObject.ОтражениеЗарплатыВБухучете</v8:Type>
				<v8:Type>cfg:CatalogObject.ОбособленныеПодразделенияОрганизаций</v8:Type>
				<v8:Type>cfg:CatalogObject.СтатьиНеоперационныхРасходов</v8:Type>
				<v8:Type>cfg:CatalogObject.ВидыЛьготПоНДФЛ</v8:Type>
				<v8:Type>cfg:CatalogObject.СхемыНалоговогоУчетаПоДоговорамКонтрагентов</v8:Type>
				<v8:Type>cfg:DocumentObject.Партия</v8:Type>
				<v8:Type>cfg:CatalogObject.СпецификацииНоменклатуры</v8:Type>
				<v8:Type>cfg:ChartOfCharacteristicTypesObject.ВидыСубконтоХозрасчетные</v8:Type>
				<v8:Type>cfg:CatalogObject.ПараметрыТиповойОперации</v8:Type>
				<v8:Type>cfg:DocumentObject.КорректировкаОжидаемогоИПодтвержденногоНДС</v8:Type>
				<v8:Type>cfg:CatalogObject.ТипыЦенНоменклатуры</v8:Type>
				<v8:Type>cfg:DocumentObject.ЗаявлениеНаПрименениеЛьготы</v8:Type>
				<v8:Type>cfg:DocumentObject.РеализацияТоваровУслуг</v8:Type>
				<v8:Type>cfg:DocumentObject.ПередачаОС</v8:Type>
				<v8:Type>cfg:DocumentObject.ПередачаТоваров</v8:Type>
				<v8:Type>cfg:CatalogObject.ОтчетКомиссионераОПродажахПрисоединенныеФайлы</v8:Type>
				<v8:Type>cfg:DocumentObject.ГТДИмпорт</v8:Type>
				<v8:Type>cfg:DocumentObject.ПереоценкаТоваровВРознице</v8:Type>
				<v8:Type>cfg:DocumentObject.ПерерасчетПропорциональногоНДСпоТоварамИОС</v8:Type>
				<v8:Type>cfg:DocumentObject.РасчетыПоНалогуНаПрибыль</v8:Type>
				<v8:Type>cfg:DocumentObject.УстановкаЦенНоменклатуры</v8:Type>
				<v8:Type>cfg:CatalogObject.Должности</v8:Type>
				<v8:Type>cfg:DocumentObject.ПередачаНМА</v8:Type>
				<v8:Type>cfg:DocumentObject.АвансовыйОтчет</v8:Type>
				<v8:Type>cfg:CatalogObject.Склады</v8:Type>
				<v8:Type>cfg:CatalogObject.ДоговорыКонтрагентов</v8:Type>
				<v8:Type>cfg:CatalogObject.АктСверкиВзаиморасчетовПрисоединенныеФайлы</v8:Type>
				<v8:Type>cfg:CatalogObject.ПрофилиГруппДоступа</v8:Type>
				<v8:Type>cfg:CatalogObject.СтатьиНалоговыхДеклараций</v8:Type>
				<v8:Type>cfg:DocumentObject.ПокупкаПродажаВалюты</v8:Type>
				<v8:Type>cfg:CatalogObject.Банки</v8:Type>
				<v8:Type>cfg:DocumentObject.КомандировкиОрганизаций</v8:Type>
				<v8:Type>cfg:CatalogObject.ВидыОплатОрганизаций</v8:Type>
				<v8:Type>cfg:DocumentObject.ОпределениеФинансовыхРезультатов</v8:Type>
				<v8:Type>cfg:CatalogObject.ОрганизацииПрисоединенныеФайлы</v8:Type>
				<v8:Type>cfg:DocumentObject.ПлатежныйОрдерСписаниеДенежныхСредств</v8:Type>
				<v8:Type>cfg:CatalogObject.ОбщиеДанныеИнформационногоЦентра</v8:Type>
				<v8:Type>cfg:DocumentObject.Доверенность</v8:Type>
				<v8:Type>cfg:DocumentObject.ПоступлениеТоваровУслуг</v8:Type>
				<v8:Type>cfg:DocumentObject.ИзменениеПараметровНачисленияАмортизацииНМА</v8:Type>
				<v8:Type>cfg:CatalogObject.СчетНаОплатуПоставщикаПрисоединенныеФайлы</v8:Type>
				<v8:Type>cfg:DocumentObject.АктОбОказанииПроизводственныхУслуг</v8:Type>
				<v8:Type>cfg:CatalogObject.Пользователи</v8:Type>
				<v8:Type>cfg:DocumentObject.ВозвратТоваровОтПокупателя</v8:Type>
				<v8:Type>cfg:DocumentObject.КадровыйПеревод</v8:Type>
				<v8:Type>cfg:DocumentObject.СправкаОДоходах</v8:Type>
				<v8:Type>cfg:CatalogObject.РеализацияУслугПоПереработкеПрисоединенныеФайлы</v8:Type>
				<v8:Type>cfg:DocumentObject.ПередачаМалоценныхАктивовВЭксплуатацию</v8:Type>
				<v8:Type>cfg:CatalogObject.Комиссии</v8:Type>
				<v8:Type>cfg:CatalogObject.ТипыИнформацииИнформационногоЦентра</v8:Type>
				<v8:Type>cfg:CatalogObject.ИнвентаризацияТоваровНаСкладеПрисоединенныеФайлы</v8:Type>
				<v8:Type>cfg:CatalogObject.СпособыОкругленияПриВыплатеЗарплаты</v8:Type>
				<v8:Type>cfg:DocumentObject.РегистрацияВходящегоНалоговогоДокумента</v8:Type>
				<v8:Type>cfg:DocumentObject.ВводСведенийОбИндексированномДоходе</v8:Type>
				<v8:Type>cfg:CatalogObject.СпособыОтраженияРасходовПоАмортизации</v8:Type>
				<v8:Type>cfg:DocumentObject.ВводВЭксплуатациюОС</v8:Type>
				<v8:Type>cfg:CatalogObject.ПользовательскиеНастройкиОтчетов</v8:Type>
				<v8:Type>cfg:CatalogObject.КонтактныеЛица</v8:Type>
				<v8:Type>cfg:CatalogObject.БанковскиеСчета</v8:Type>
				<v8:Type>cfg:CatalogObject.ГТДИмпортПрисоединенныеФайлы</v8:Type>
				<v8:Type>cfg:DocumentObject.ИнвентаризацияНЗП</v8:Type>
				<v8:Type>cfg:ChartOfAccountsObject.Хозрасчетный</v8:Type>
				<v8:Type>cfg:CatalogObject.СтатьиЗатрат</v8:Type>
				<v8:Type>cfg:DocumentObject.ПоступлениеИзПереработки</v8:Type>
				<v8:Type>cfg:CatalogObject.ГруппыДоступаФизическихЛиц</v8:Type>
				<v8:Type>cfg:CatalogObject.КадровыйПереводПрисоединенныеФайлы</v8:Type>
				<v8:Type>cfg:CatalogObject.Номенклатура</v8:Type>
				<v8:Type>cfg:CatalogObject.СобытияОС</v8:Type>
				<v8:Type>cfg:CatalogObject.ОснованияУвольнения</v8:Type>
				<v8:Type>cfg:CatalogObject.НалоговыеГруппыОсновныхСредств</v8:Type>
				<v8:Type>cfg:CatalogObject.НазначениеЦелевыхСредств</v8:Type>
				<v8:Type>cfg:DocumentObject.РасходныйКассовыйОрдер</v8:Type>
				<v8:Type>cfg:CatalogObject.СчетНаОплатуПокупателюПрисоединенныеФайлы</v8:Type>
				<v8:Type>cfg:DocumentObject.ПеремещениеОС</v8:Type>
				<v8:Type>cfg:CatalogObject.ЦенныеБумаги</v8:Type>
				<v8:Type>cfg:DocumentObject.ВедомостьНаВыплатуЗарплатыВБанк</v8:Type>
				<v8:Type>cfg:DocumentObject.ИнвентаризацияНМА</v8:Type>
				<v8:Type>cfg:DocumentObject.ПлатежноеПоручение</v8:Type>
				<v8:Type>cfg:CatalogObject.КлассификаторКОАТУУ</v8:Type>
				<v8:Type>cfg:CatalogObject.ДоходыБудущихПериодов</v8:Type>
				<v8:Type>cfg:CatalogObject.РегламентированныеОтчеты</v8:Type>
				<v8:Type>cfg:CatalogObject.ОтчетКомитентуОПродажахПрисоединенныеФайлы</v8:Type>
				<v8:Type>cfg:CatalogObject.КонтрактныеОбязательства</v8:Type>
				<v8:Type>cfg:CatalogObject.Налоги</v8:Type>
				<v8:Type>cfg:DocumentObject.ОтчетОРозничныхПродажах</v8:Type>
				<v8:Type>cfg:CatalogObject.НомераГТД</v8:Type>
				<v8:Type>cfg:ChartOfCharacteristicTypesObject.РазделыДатЗапретаИзменения</v8:Type>
				<v8:Type>cfg:CatalogObject.КорректировкаДолгаПрисоединенныеФайлы</v8:Type>
				<v8:Type>cfg:DocumentObject.ИнвентаризацияОС</v8:Type>
				<v8:Type>cfg:CatalogObject.КатегорииЗастрахованныхЛицЕСВ</v8:Type>
				<v8:Type>cfg:CatalogObject.СхемыНалогообложения</v8:Type>
				<v8:Type>cfg:DocumentObject.ПередачаОборудованияВМонтаж</v8:Type>
				<v8:Type>cfg:CatalogObject.НачислениеЗарплатыПрисоединенныеФайлы</v8:Type>
				<v8:Type>cfg:DocumentObject.КомплектацияНоменклатуры</v8:Type>
				<v8:Type>cfg:CatalogObject.ПоступлениеДопРасходовПрисоединенныеФайлы</v8:Type>
				<v8:Type>cfg:CatalogObject.ФинансовыеИнвестиции</v8:Type>
				<v8:Type>cfg:DocumentObject.СписаниеОС</v8:Type>
				<v8:Type>cfg:CatalogObject.ГруппыВнешнихПользователей</v8:Type>
				<v8:Type>cfg:CatalogObject.ВидыРегистровУчета</v8:Type>
				<v8:Type>cfg:CatalogObject.СхемыРеализации</v8:Type>
				<v8:Type>cfg:DocumentObject.ИндексацияОС</v8:Type>
				<v8:Type>cfg:CatalogObject.Контрагенты</v8:Type>
				<v8:Type>cfg:ChartOfCalculationTypesObject.Начисления</v8:Type>
				<v8:Type>cfg:CatalogObject.ВидыДоходовНДФЛ</v8:Type>
				<v8:Type>cfg:CatalogObject.НалоговаяНакладнаяПрисоединенныеФайлы</v8:Type>
				<v8:Type>cfg:DocumentObject.МодернизацияОС</v8:Type>
				<v8:Type>cfg:CatalogObject.ВидыНалоговойДеятельности</v8:Type>
				<v8:Type>cfg:CatalogObject.СтатьиДвиженияДенежныхСредств</v8:Type>
				<v8:Type>cfg:ChartOfCalculationTypesObject.Удержания</v8:Type>
				<v8:Type>cfg:DocumentObject.ИзменениеПараметровРасчетаИндексации</v8:Type>
				<v8:Type>cfg:ChartOfCharacteristicTypesObject.ДополнительныеРеквизитыИСведения</v8:Type>
				<v8:Type>cfg:CatalogObject.ДополнительныеОтчетыИОбработки</v8:Type>
				<v8:Type>cfg:DocumentObject.ПеремещениеТоваров</v8:Type>
				<v8:Type>cfg:CatalogObject.Резервы</v8:Type>
				<v8:Type>cfg:DocumentObject.КорректировкаДолга</v8:Type>
				<v8:Type>cfg:DocumentObject.ПеремещениеМалоценныхАктивовВЭксплуатации</v8:Type>
				<v8:Type>cfg:DocumentObject.УстановкаГарантийныхСроковНалоговыйУчет</v8:Type>
				<v8:Type>cfg:DocumentObject.ПринятиеКУчетуНМА</v8:Type>
				<v8:Type>cfg:CatalogObject.ДоговорыКонтрагентовПрисоединенныеФайлы</v8:Type>
				<v8:Type>cfg:CatalogObject.РасходныйКассовыйОрдерПрисоединенныеФайлы</v8:Type>
				<v8:Type>cfg:CatalogObject.СертификатыКлючейЭлектроннойПодписиИШифрования</v8:Type>
				<v8:Type>cfg:CatalogObject.ДополнительныеГарантииВСодействииТрудоустройству</v8:Type>
				<v8:Type>cfg:CatalogObject.РегистрацияВходящегоНалоговогоДокументаПрисоединенныеФайлы</v8:Type>
				<v8:Type>cfg:CatalogObject.ВидыДоговоровПоГК</v8:Type>
				<v8:Type>cfg:CatalogObject.ПредопределенныеВариантыОтчетов</v8:Type>
				<v8:Type>cfg:DocumentObject.ОприходованиеТоваров</v8:Type>
				<v8:Type>cfg:CatalogObject.ВидыКонтактнойИнформации</v8:Type>
				<v8:Type>cfg:DocumentObject.ИзменениеНалоговогоНазначенияТЗР</v8:Type>
				<v8:Type>cfg:DocumentObject.ВыработкаОС</v8:Type>
				<v8:Type>cfg:CatalogObject.БиологическиеАктивы</v8:Type>
				<v8:Type>cfg:CatalogObject.КлассификаторУКТВЭД</v8:Type>
				<v8:Type>cfg:DocumentObject.ИзменениеСпособовОтраженияРасходовПоАмортизацииОС</v8:Type>
				<v8:Type>cfg:CatalogObject.ТиповыеОперации</v8:Type>
				<v8:Type>cfg:CatalogObject.ВедомостьНаВыплатуЗарплатыВКассуПрисоединенныеФайлы</v8:Type>
				<v8:Type>cfg:DocumentObject.ИнвентаризацияРасчетовСКонтрагентами</v8:Type>
				<v8:Type>cfg:CatalogObject.Календари</v8:Type>
				<v8:Type>cfg:CatalogObject.ВнешниеПользователи</v8:Type>
				<v8:Type>cfg:DocumentObject.ПодготовкаКПередачеОС</v8:Type>
				<v8:Type>cfg:CatalogObject.КлассификаторЕдиницИзмерения</v8:Type>
				<v8:Type>cfg:CatalogObject.ЗначенияСвойствОбъектов</v8:Type>
				<v8:Type>cfg:CatalogObject.ЗначенияСвойствОбъектовИерархия</v8:Type>
				<v8:Type>cfg:DocumentObject.ПеремещениеНМА</v8:Type>
				<v8:Type>cfg:CatalogObject.ГруппыДоступа</v8:Type>
				<v8:Type>cfg:CatalogObject.ПараметрыВыработкиОС</v8:Type>
				<v8:Type>cfg:CatalogObject.НаборыДополнительныхРеквизитовИСведений</v8:Type>
				<v8:Type>cfg:DocumentObject.ИзменениеСпособовОтраженияРасходовПоАмортизацииНМА</v8:Type>
				<v8:Type>cfg:CatalogObject.ПроизводственныеКалендари</v8:Type>
				<v8:Type>cfg:CatalogObject.НазначенияИспользования</v8:Type>
				<v8:Type>cfg:DocumentObject.ИзменениеГрафиковАмортизацииОС</v8:Type>
				<v8:Type>cfg:DocumentObject.ЗакрытиеМесяца</v8:Type>
				<v8:Type>cfg:CatalogObject.ПодразделенияОрганизаций</v8:Type>
				<v8:Type>cfg:DocumentObject.ИзменениеСостоянияОС</v8:Type>
				<v8:Type>cfg:DocumentObject.ПартияМалоценныхАктивовВЭксплуатации</v8:Type>
				<v8:Type>cfg:CatalogObject.Файлы</v8:Type>
				<v8:Type>cfg:CatalogObject.АвансовыйОтчетПрисоединенныеФайлы</v8:Type>
				<v8:Type>cfg:DocumentObject.ОтчетКомиссионераОПродажах</v8:Type>
				<v8:Type>cfg:CatalogObject.Сотрудники</v8:Type>
				<v8:Type>cfg:DocumentObject.ПриемНаРаботу</v8:Type>
				<v8:Type>cfg:CatalogObject.НазначенияНаличныхДенежныхСредств</v8:Type>
				<v8:Type>cfg:DocumentObject.НормированиеРасходовПоНалогуНаПрибыль</v8:Type>
				<v8:Type>cfg:CatalogObject.ВозвратТоваровПоставщикуПрисоединенныеФайлы</v8:Type>
				<v8:Type>cfg:CatalogObject.НоменклатурныеГруппы</v8:Type>
				<v8:Type>cfg:CatalogObject.СтатьиДоходов</v8:Type>
				<v8:Type>cfg:DocumentObject.РеализацияУслугПоПереработке</v8:Type>
				<v8:Type>cfg:CatalogObject.ГруппыПользователей</v8:Type>
				<v8:Type>cfg:CatalogObject.РолиКонтактныхЛиц</v8:Type>
				<v8:Type>cfg:CatalogObject.ПоступлениеТоваровУслугПрисоединенныеФайлы</v8:Type>
				<v8:Type>cfg:DocumentObject.УстановкаПорядкаЗакрытияПодразделений</v8:Type>
				<v8:Type>cfg:DocumentObject.ДепонированиеЗарплаты</v8:Type>
				<v8:Type>cfg:DocumentObject.ОтражениеВзаиморасчетовСКонтрагентамиВ1ДФ</v8:Type>
				<v8:Type>cfg:DocumentObject.Увольнение</v8:Type>
				<v8:Type>cfg:CatalogObject.ВедомостьНаВыплатуЗарплатыВБанкПрисоединенныеФайлы</v8:Type>
				<v8:Type>cfg:DocumentObject.МодернизацияНМА</v8:Type>
				<v8:Type>cfg:DocumentObject.ИзменениеНалоговогоНазначенияОС</v8:Type>
				<v8:Type>cfg:CatalogObject.НематериальныеАктивы</v8:Type>
				<v8:Type>cfg:CatalogObject.ВидыВыплат</v8:Type>
				<v8:Type>cfg:CatalogObject.ИдентификаторыОбъектовМетаданных</v8:Type>
				<v8:Type>cfg:DocumentObject.ЗаявкаНаПокупкуПродажуВалюты</v8:Type>
				<v8:Type>cfg:CatalogObject.ВариантыОтчетов</v8:Type>
				<v8:Type>cfg:DocumentObject.ИзменениеПараметровНачисленияАмортизацииОС</v8:Type>
				<v8:Type>cfg:CatalogObject.ВидыДокументовФизическихЛиц</v8:Type>
				<v8:Type>cfg:DocumentObject.АктСверкиВзаиморасчетов</v8:Type>
				<v8:Type>cfg:CatalogObject.ВидыВзаиморасчетов</v8:Type>
				<v8:Type>cfg:DocumentObject.ИнвентаризацияТоваровНаСкладе</v8:Type>
				<v8:Type>cfg:DocumentObject.СчетНаОплатуПоставщика</v8:Type>
				<v8:Type>cfg:CatalogObject.СпособыОтраженияЗарплатыВРеглУчете</v8:Type>
				<v8:Type>cfg:DocumentObject.ОтчетКомитентуОПродажах</v8:Type>
				<v8:Type>cfg:DocumentObject.ДокументРасчетовСКонтрагентом</v8:Type>
				<v8:Type>cfg:CatalogObject.ПрограммыЭлектроннойПодписиИШифрования</v8:Type>
				<v8:Type>cfg:CatalogObject.Гарантии</v8:Type>
				<v8:Type>cfg:DocumentObject.ПоступлениеНаРасчетныйСчет</v8:Type>
				<v8:Type>cfg:DocumentObject.СписаниеТоваров</v8:Type>
				<v8:Type>cfg:CatalogObject.АктОбОказанииПроизводственныхУслугПрисоединенныеФайлы</v8:Type>
				<v8:Type>cfg:CatalogObject.НалоговыеИнспекции</v8:Type>
				<v8:Type>cfg:DocumentObject.ТребованиеНакладная</v8:Type>
				<v8:Type>cfg:CatalogObject.ОперацияБухПрисоединенныеФайлы</v8:Type>
				<v8:Type>cfg:CatalogObject.СписаниеСРасчетногоСчетаПрисоединенныеФайлы</v8:Type>
				<v8:Type>cfg:CatalogObject.НалоговыеНазначенияАктивовИЗатрат</v8:Type>
				<v8:Type>cfg:CatalogObject.Приложение2КНалоговойНакладнойПрисоединенныеФайлы</v8:Type>
				<v8:Type>cfg:CatalogObject.ДепонированиеЗарплатыПрисоединенныеФайлы</v8:Type>
				<v8:Type>cfg:DocumentObject.РегламентированныйОтчет</v8:Type>
				<v8:Type>cfg:DocumentObject.ИзменениеПараметровРасчетаИндексацииПоДолжностям</v8:Type>
				<v8:Type>cfg:CatalogObject.РасходыБудущихПериодов</v8:Type>
				<v8:Type>cfg:DocumentObject.ВводНачальныхОстатков</v8:Type>
				<v8:Type>cfg:DocumentObject.РегистрУчета</v8:Type>
				<v8:Type>cfg:CatalogObject.ПриходныйКассовыйОрдерПрисоединенныеФайлы</v8:Type>
				<v8:Type>cfg:DocumentObject.ОперацияБух</v8:Type>
				<v8:Type>cfg:CatalogObject.Субконто</v8:Type>
				<v8:Type>cfg:DocumentObject.РегистрацияСтоимостиПриобретенияОСПропорциональноОблагаемыхНДС</v8:Type>
				<v8:Type>cfg:CatalogObject.ПриемНаРаботуПрисоединенныеФайлы</v8:Type>
				<v8:Type>cfg:DocumentObject.ПереоценкаОС</v8:Type>
				<v8:Type>cfg:CatalogObject.СписокСтатейЗатратВключенныхВБазуРаспределенияКосвенныхРасходов</v8:Type>
				<v8:Type>cfg:DocumentObject.ВедомостьНаВыплатуЗарплатыВКассу</v8:Type>
				<v8:Type>cfg:DocumentObject.РегистрацияАвансовВНалоговомУчете</v8:Type>
				<v8:Type>cfg:CatalogObject.Валюты</v8:Type>
				<v8:Type>cfg:DocumentObject.ПоступлениеДопРасходов</v8:Type>
				<v8:Type>cfg:DocumentObject.СписаниеДепонентовВДоходыОрганизаций</v8:Type>
				<v8:Type>cfg:DocumentObject.ВедомостьНаВыплатуЗарплаты</v8:Type>
				<v8:Type>cfg:CatalogObject.ГодовыеГрафикиАмортизацииОС</v8:Type>
			</Source>
			<Event>BeforeDelete</Event>
			<Handler>CommonModule.АвтономнаяРаботаОбменДаннымиСобытия.АвтономнаяРаботаЗарегистрироватьУдалениеПередУдалением</Handler>
		</Properties>
	</EventSubscription>
</MetaDataObject>